<?xml version="1.0" encoding="utf-8" ?>
<dwsync>
<file name="financial-statement-pssap.php" server="cedar-test//srv/www/htdocs/intranet/www/" local="131242532744616920" remote="131242532790000000" Dst="2" />
<file name="fs_notes_landing.php" server="cedar-test//srv/www/htdocs/intranet/www/" local="131242532194463330" remote="131242532220000000" Dst="2" />
<file name="note_1.php" server="cedar-test//srv/www/htdocs/intranet/www/" local="131242531873887070" remote="131242531900000000" Dst="2" />
<file name="note_19.php" server="cedar-test//srv/www/htdocs/intranet/www/" local="131242527138672500" remote="131242527160000000" Dst="2" />
<file name="note_18.php" server="cedar-test//srv/www/htdocs/intranet/www/" local="131242527443729090" remote="131242527470000000" Dst="2" />
<file name="note_17.php" server="cedar-test//srv/www/htdocs/intranet/www/" local="131243477302034780" remote="131243477430000000" Dst="2" />
<file name="note_16.php" server="cedar-test//srv/www/htdocs/intranet/www/" local="131242529457475350" remote="131242529480000000" Dst="2" />
<file name="note_15.php" server="cedar-test//srv/www/htdocs/intranet/www/" local="131242529854420920" remote="131242529880000000" Dst="2" />
<file name="note_14.php" server="cedar-test//srv/www/htdocs/intranet/www/" local="131242530341665170" remote="131242530370000000" Dst="2" />
<file name="note_13.php" server="cedar-test//srv/www/htdocs/intranet/www/" local="131242530659131340" remote="131242530680000000" Dst="2" />
<file name="note_12.php" server="cedar-test//srv/www/htdocs/intranet/www/" local="131242530941528020" remote="131242530970000000" Dst="2" />
<file name="note_11.php" server="cedar-test//srv/www/htdocs/intranet/www/" local="131242531210000000" remote="131242531240000000" Dst="2" />
<file name="note_10.php" server="cedar-test//srv/www/htdocs/intranet/www/" local="131242531514261600" remote="131242531540000000" Dst="2" />
<file name="note_9.php" server="cedar-test//srv/www/htdocs/intranet/www/" local="131242523332687150" remote="131242523360000000" Dst="2" />
<file name="note_8.php" server="cedar-test//srv/www/htdocs/intranet/www/" local="131242523577514220" remote="131242523630000000" Dst="2" />
<file name="note_6.php" server="cedar-test//srv/www/htdocs/intranet/www/" local="131242524267455980" remote="131242524300000000" Dst="2" />
<file name="note_7.php" server="cedar-test//srv/www/htdocs/intranet/www/" local="131242523924190010" remote="131242523950000000" Dst="2" />
<file name="note_5.php" server="cedar-test//srv/www/htdocs/intranet/www/" local="131242525757528590" remote="131242525790000000" Dst="2" />
<file name="note_4.php" server="cedar-test//srv/www/htdocs/intranet/www/" local="131242526107274530" remote="131242526120000000" Dst="2" />
<file name="note_3.php" server="cedar-test//srv/www/htdocs/intranet/www/" local="131242526447910530" remote="131242526470000000" Dst="2" />
<file name="note_2.php" server="cedar-test//srv/www/htdocs/intranet/www/" local="131242526779166990" remote="131242526800000000" Dst="2" />
</dwsync>